XiandaiOpenglJiaocheng/README.md
XiandaiOpenglJiaocheng/__init__.py
XiandaiOpenglJiaocheng/__main__.py
XiandaiOpenglJiaocheng/file.epub
XiandaiOpenglJiaocheng/index.html
XiandaiOpenglJiaocheng/css/__init__.py
XiandaiOpenglJiaocheng/css/annotations.css
XiandaiOpenglJiaocheng/css/main.css
XiandaiOpenglJiaocheng/css/normalize.css
XiandaiOpenglJiaocheng/css/popup.css
XiandaiOpenglJiaocheng/font/__init__.py
XiandaiOpenglJiaocheng/font/fontello.eot
XiandaiOpenglJiaocheng/font/fontello.svg
XiandaiOpenglJiaocheng/font/fontello.ttf
XiandaiOpenglJiaocheng/font/fontello.woff
XiandaiOpenglJiaocheng/img/__init__.py
XiandaiOpenglJiaocheng/img/annotator-glyph-sprite.png
XiandaiOpenglJiaocheng/img/annotator-icon-sprite.png
XiandaiOpenglJiaocheng/img/apple-touch-icon.png
XiandaiOpenglJiaocheng/img/cancelfullscreen.png
XiandaiOpenglJiaocheng/img/close.png
XiandaiOpenglJiaocheng/img/fullscreen.png
XiandaiOpenglJiaocheng/img/loader.gif
XiandaiOpenglJiaocheng/img/menu-icon.png
XiandaiOpenglJiaocheng/img/save.png
XiandaiOpenglJiaocheng/img/saved.png
XiandaiOpenglJiaocheng/img/settings-s.png
XiandaiOpenglJiaocheng/img/settings.png
XiandaiOpenglJiaocheng/img/star.png
XiandaiOpenglJiaocheng/js/__init__.py
XiandaiOpenglJiaocheng/js/epub.js
XiandaiOpenglJiaocheng/js/epub.min.js
XiandaiOpenglJiaocheng/js/epub.min.map
XiandaiOpenglJiaocheng/js/hooks.min.js
XiandaiOpenglJiaocheng/js/hooks.min.map
XiandaiOpenglJiaocheng/js/reader.js
XiandaiOpenglJiaocheng/js/reader.js.map
XiandaiOpenglJiaocheng/js/reader.min.js
XiandaiOpenglJiaocheng/js/reader.min.map
XiandaiOpenglJiaocheng/js/hooks/__init__.py
XiandaiOpenglJiaocheng/js/hooks/extensions/__init__.py
XiandaiOpenglJiaocheng/js/hooks/extensions/highlight.js
XiandaiOpenglJiaocheng/js/libs/__init__.py
XiandaiOpenglJiaocheng/js/libs/jquery.min.js
XiandaiOpenglJiaocheng/js/libs/localforage.min.js
XiandaiOpenglJiaocheng/js/libs/screenfull.js
XiandaiOpenglJiaocheng/js/libs/screenfull.min.js
XiandaiOpenglJiaocheng/js/libs/zip.min.js
xiandai_opengl_jiaocheng-2024.2.29.0.dist-info/METADATA
xiandai_opengl_jiaocheng-2024.2.29.0.dist-info/WHEEL
xiandai_opengl_jiaocheng-2024.2.29.0.dist-info/entry_points.txt
xiandai_opengl_jiaocheng-2024.2.29.0.dist-info/top_level.txt
xiandai_opengl_jiaocheng-2024.2.29.0.dist-info/RECORD
